redditwarp/ASYNC.py
redditwarp/SYNC.py
redditwarp/__about__.py
redditwarp/__init__.py
redditwarp/_cli/__init__.pyi
redditwarp/_cli/access_token.py
redditwarp/_cli/comment_tree.py
redditwarp/_cli/exchange_authorization_code.py
redditwarp/_cli/implicit_flow.py
redditwarp/_cli/refresh_token.py
redditwarp/_cli/revoke_token.py
redditwarp/auth/ASYNC.py
redditwarp/auth/SYNC.py
redditwarp/auth/__init__.py
redditwarp/auth/exceptions.py
redditwarp/auth/grants.py
redditwarp/auth/token.py
redditwarp/auth/token_obtainment_client_ASYNC.py
redditwarp/auth/token_obtainment_client_SYNC.py
redditwarp/auth/token_revocation_client_ASYNC.py
redditwarp/auth/token_revocation_client_SYNC.py
redditwarp/auth/types.py
redditwarp/auth/utils.py
redditwarp/client_ASYNC.py
redditwarp/client_SYNC.py
redditwarp/core/ASYNC.py
redditwarp/core/SYNC.py
redditwarp/core/__init__.py
redditwarp/core/authorizer_ASYNC.py
redditwarp/core/authorizer_SYNC.py
redditwarp/core/const.py
redditwarp/core/direct_by_origin_ASYNC.py
redditwarp/core/direct_by_origin_SYNC.py
redditwarp/core/exceptions.py
redditwarp/core/follow_redirects_value_none_means_ASYNC.py
redditwarp/core/follow_redirects_value_none_means_SYNC.py
redditwarp/core/grants.py
redditwarp/core/http_client_ASYNC.py
redditwarp/core/http_client_SYNC.py
redditwarp/core/rate_limited_ASYNC.py
redditwarp/core/rate_limited_SYNC.py
redditwarp/core/recorded_ASYNC.py
redditwarp/core/recorded_SYNC.py
redditwarp/core/reddit_please_send_json_ASYNC.py
redditwarp/core/reddit_please_send_json_SYNC.py
redditwarp/core/reddit_token_obtainment_client_ASYNC.py
redditwarp/core/reddit_token_obtainment_client_SYNC.py
redditwarp/core/ua_ASYNC.py
redditwarp/core/ua_SYNC.py
redditwarp/dark/ASYNC.py
redditwarp/dark/SYNC.py
redditwarp/dark/__init__.py
redditwarp/dark/auth/ASYNC.py
redditwarp/dark/auth/SYNC.py
redditwarp/dark/auth/__init__.py
redditwarp/dark/auth/exceptions.py
redditwarp/dark/auth/token.py
redditwarp/dark/auth/token_obtainment_client_ASYNC.py
redditwarp-1.3.0.dist-info/LICENSE
redditwarp-1.3.0.dist-info/METADATA
redditwarp-1.3.0.dist-info/WHEEL
redditwarp-1.3.0.dist-info/RECORD
